EVTUHLIB/__init__.py
EVTUHLIB/main.py
EVTUHLIB-3.0.0.dist-info/METADATA
EVTUHLIB-3.0.0.dist-info/WHEEL
EVTUHLIB-3.0.0.dist-info/top_level.txt
EVTUHLIB-3.0.0.dist-info/RECORD
