Metadata-Version: 2.1
Name: EVTUHLIB
Version: 3.0.0
Summary: ...
Home-page: https://sweet-store.ru
Author: Evtushenko Vladislav
Author-email: evtuh545@gmail.com
Keywords: evtuh evtuh
Classifier: Programming Language :: Python :: 3.11
Classifier: License :: OSI Approved :: MIT License
Classifier: Operating System :: OS Independent
Requires-Python: >=3.6
Requires-Dist: art
